pyviewfactor/11pyviewfactor.py
pyviewfactor/BKP_1.py
pyviewfactor/LAST_BKP_nanpyviewfactor.py
pyviewfactor/OLD.py
pyviewfactor/__init__.py
pyviewfactor/_version.py
pyviewfactor/pvf_geometry_preprocess.py
pyviewfactor/pvf_integrators.py
pyviewfactor/pvf_plot.py
pyviewfactor/pvf_viewfactor_computations.py
pyviewfactor/pvf_visibility_obstruction.py
pyviewfactor/pyviewfactor.py
pyviewfactor/pyviewfactor_906.py
pyviewfactor/pyviewfactor_BKP12-06.py
pyviewfactor/pyviewfactor_BKP_130625.py
pyviewfactor/pyviewfactor_integration.py
pyviewfactor/pyviewfactor_refactor_base.py
pyviewfactor/pyviewfactor_v1.py
pyviewfactor/pyviewfactor_vis_obs_OK.py
pyviewfactor/pyviewfactorv2.py
test/__init__.py
test/test_geometry_preprocess.py
test/test_plot.py
test/test_utils.py
test/test_view_factor.py
test/test_visibility_obstruction.py
pyviewfactor-1.0.0.dist-info/LICENSE.txt
pyviewfactor-1.0.0.dist-info/METADATA
pyviewfactor-1.0.0.dist-info/WHEEL
pyviewfactor-1.0.0.dist-info/top_level.txt
pyviewfactor-1.0.0.dist-info/RECORD
