Metadata-Version: 2.1
Name: pyviewfactor
Version: 1.0.0
Summary: "A lightweight open-source Python library for exact view-factor computations on polygonal meshes"
Home-page: https://gitlab.com/arep-dev/pyViewFactor/
Author: Mateusz BOGDAN, Edouard WALTHER, Marc ALECIAN, Mina CHAPON
Author-email: mateusz.bogdan@arep.fr
License: MIT
Keywords: radiative-transfer,radiation,vtk,geometry,viewfactor,visibility
Classifier: Programming Language :: Python :: 3
Classifier: License :: OSI Approved :: MIT License
Classifier: Topic :: Scientific/Engineering :: Physics
Classifier: Operating System :: OS Independent
Requires-Python: >=3.8
License-File: LICENSE.txt
Requires-Dist: numpy >=1.19
Requires-Dist: scipy >=1.7
Requires-Dist: numba >=0.55
Requires-Dist: pyvista >=0.32
